parse_xspec/__init__.py
parse_xspec/models.py
parse_xspec-0.1.0.dist-info/LICENSE
parse_xspec-0.1.0.dist-info/METADATA
parse_xspec-0.1.0.dist-info/WHEEL
parse_xspec-0.1.0.dist-info/top_level.txt
parse_xspec-0.1.0.dist-info/RECORD
