Metadata-Version: 2.1
Name: parse-xspec
Version: 0.1.0
Summary: Parse files used by XSPEC (highly experimental)
Home-page: https://github.com/cxcsds/parse_xspec
Author: Doug Burke
Author-email: dburke.gw@gmail.com
License: UNKNOWN
Project-URL: Bug Tracker, https://github.com/cxcsds/parse_xspec/issues
Platform: UNKNOWN
Classifier: Programming Language :: Python :: 3
Classifier: License :: OSI Approved :: GNU General Public License v3 or later (GPLv3+)
Classifier: Operating System :: OS Independent
Classifier: Intended Audience :: Science/Research
Classifier: Topic :: Scientific/Engineering :: Astronomy
Classifier: Topic :: Scientific/Engineering :: Physics
Requires-Python: >=3.6
License-File: LICENSE
